[{"team_id": 1448, "team": "Western Wash.", "id": "3217", "name": "Stephanie Dressel", "year": "Redshirt Freshman", "hometown": "Gig Harbor, WA", "high_school": "Gig Harbor", "previous_school": null, "height": "6'2\"", "position": "C/F", "jersey": "4", "url": "/sports/womens-basketball/roster/stephanie-dressel/3217", "season": "2002-03"}, {"team_id": 1448, "team": "Western Wash.", "id": "3215", "name": "Tessa DeBoer", "year": "Junior", "hometown": "Lynden, WA", "high_school": "Lynden Christian", "previous_school": null, "height": "5'11\"", "position": "F", "jersey": "10", "url": "/sports/womens-basketball/roster/tessa-deboer/3215", "season": "2002-03"}, {"team_id": 1448, "team": "Western Wash.", "id": "3223", "name": "Megan Quarterman", "year": "Senior", "hometown": "Granite Falls, WA", "high_school": "Granite Falls", "previous_school": null, "height": "5'9\"", "position": "G", "jersey": "12", "url": "/sports/womens-basketball/roster/megan-quarterman/3223", "season": "2002-03"}, {"team_id": 1448, "team": "Western Wash.", "id": "3220", "name": "Samantha Hubbard", "year": "Freshman", "hometown": "Carbonado, WA", "high_school": "White River", "previous_school": null, "height": "5'6\"", "position": "G", "jersey": "20", "url": "/sports/womens-basketball/roster/samantha-hubbard/3220", "season": "2002-03"}, {"team_id": 1448, "team": "Western Wash.", "id": "3216", "name": "Tina Donahue", "year": "Redshirt Freshman", "hometown": "Stanwood, WA", "high_school": "Stanwood", "previous_school": null, "height": null, "position": "F", "jersey": "21", "url": "/sports/womens-basketball/roster/tina-donahue/3216", "season": "2002-03"}, {"team_id": 1448, "team": "Western Wash.", "id": "3222", "name": "Stacey Miller", "year": "Senior", "hometown": "Bellingham, WA", "high_school": "Sehome", "previous_school": null, "height": "5'11\"", "position": "F", "jersey": "22", "url": "/sports/womens-basketball/roster/stacey-miller/3222", "season": "2002-03"}, {"team_id": 1448, "team": "Western Wash.", "id": "3214", "name": "Dachelle Davis", "year": "Freshman", "hometown": "Yakima, WA", "high_school": "West Valley", "previous_school": null, "height": "5'6\"", "position": "G", "jersey": "30", "url": "/sports/womens-basketball/roster/dachelle-davis/3214", "season": "2002-03"}, {"team_id": 1448, "team": "Western Wash.", "id": "3221", "name": "Jenn McGillivray", "year": "Junior", "hometown": "Salem, OR", "high_school": "South Salem", "previous_school": null, "height": "5'11\"", "position": "F", "jersey": "32", "url": "/sports/womens-basketball/roster/jenn-mcgillivray/3221", "season": "2002-03"}, {"team_id": 1448, "team": "Western Wash.", "id": "3218", "name": "Kristy Eggen", "year": "Senior", "hometown": "Shoreline, WA", "high_school": "Shorecrest", "previous_school": null, "height": "5'4\"", "position": "G", "jersey": "33", "url": "/sports/womens-basketball/roster/kristy-eggen/3218", "season": "2002-03"}, {"team_id": 1448, "team": "Western Wash.", "id": "3219", "name": "Jodi Gerald", "year": "Sophomore", "hometown": "Puyallup, WA", "high_school": "Cascade Christian", "previous_school": null, "height": "5'10\"", "position": "F", "jersey": "42", "url": "/sports/womens-basketball/roster/jodi-gerald/3219", "season": "2002-03"}, {"team_id": 1448, "team": "Western Wash.", "id": "3224", "name": "Susan Rodgers", "year": "Sophomore", "hometown": "Gig Harbor, WA", "high_school": "Peninsula", "previous_school": null, "height": "6'6\"", "position": "C", "jersey": "50", "url": "/sports/womens-basketball/roster/susan-rodgers/3224", "season": "2002-03"}, {"team_id": 1448, "team": "Western Wash.", "id": "3225", "name": "Megan Toth", "year": "Junior", "hometown": "Arlington, WA", "high_school": "Arlington", "previous_school": null, "height": null, "position": "F", "jersey": "55", "url": "/sports/womens-basketball/roster/megan-toth/3225", "season": "2002-03"}]