[{"team_id": 164, "team": "UConn", "id": "11736", "name": "Aaliyah Edwards", "year": "Sophomore", "hometown": "Kingston, Ontario", "high_school": null, "previous_school": "Crestwood Preparatory College", "height": "6'3\"", "position": "Forward", "jersey": "3", "url": "/sports/womens-basketball/roster/aaliyah-edwards/11736", "season": "2000-01"}, {"team_id": 164, "team": "UConn", "id": "11743", "name": "Saylor Poffenbarger", "year": "Freshman", "hometown": "Middletown, Md.", "high_school": null, "previous_school": "Middletown HS", "height": "6'2\"", "position": "Guard", "jersey": "4", "url": "/sports/womens-basketball/roster/saylor-poffenbarger/11743", "season": "2000-01"}, {"team_id": 164, "team": "UConn", "id": "11734", "name": "Paige Bueckers", "year": "Sophomore", "hometown": "Hopkins, Minn.", "high_school": null, "previous_school": "Hopkins HS", "height": "5'11\"", "position": "Guard", "jersey": "5", "url": "/sports/womens-basketball/roster/paige-bueckers/11734", "season": "2000-01"}, {"team_id": 164, "team": "UConn", "id": "11741", "name": "Nika M\u00fchl", "year": "Sophomore", "hometown": "Zagreb, Croatia", "high_school": null, "previous_school": "III. Gimnazija Zagreb", "height": "5'10\"", "position": "Guard", "jersey": "10", "url": "/sports/womens-basketball/roster/nika-m-hl/11741", "season": "2000-01"}, {"team_id": 164, "team": "UConn", "id": "11740", "name": "Mir McLean", "year": "Sophomore", "hometown": "Baltimore, Md.", "high_school": null, "previous_school": "Roland Park Country School", "height": "5'11\"", "position": "Forward", "jersey": "11", "url": "/sports/womens-basketball/roster/mir-mclean/11740", "season": "2000-01"}, {"team_id": 164, "team": "UConn", "id": "11745", "name": "Christyn Williams", "year": "Senior", "hometown": "Little Rock, Ark.", "high_school": null, "previous_school": "Central Arkansas Christian", "height": "5'11\"", "position": "Guard", "jersey": "13", "url": "/sports/womens-basketball/roster/christyn-williams/11745", "season": "2000-01"}, {"team_id": 164, "team": "UConn", "id": "11764", "name": "Dorka Juh\u00e1sz", "year": "Graduate Student", "hometown": "Pecs, Hungary", "high_school": null, "previous_school": "Ohio State", "height": "6'5\"", "position": "Forward", "jersey": "14", "url": "/sports/womens-basketball/roster/dorka-juh-sz/11764", "season": "2000-01"}, {"team_id": 164, "team": "UConn", "id": "11742", "name": "Olivia Nelson-Ododa", "year": "Senior", "hometown": "Winder, Ga.", "high_school": null, "previous_school": "Winder Barrow HS", "height": "6'5\"", "position": "Forward", "jersey": "20", "url": "/sports/womens-basketball/roster/olivia-nelson-ododa/11742", "season": "2000-01"}, {"team_id": 164, "team": "UConn", "id": "11744", "name": "Evina Westbrook", "year": "Redshirt Senior", "hometown": "Salem, Ore.", "high_school": null, "previous_school": "Tennessee", "height": "6'0\"", "position": "Guard", "jersey": "22", "url": "/sports/womens-basketball/roster/evina-westbrook/11744", "season": "2000-01"}, {"team_id": 164, "team": "UConn", "id": "11737", "name": "Piath Gabriel", "year": "Sophomore", "hometown": "Manchester, N.H.", "high_school": null, "previous_school": "Bradford Christian Academy", "height": "6'5\"", "position": "Forward", "jersey": "32", "url": "/sports/womens-basketball/roster/piath-gabriel/11737", "season": "2000-01"}, {"team_id": 164, "team": "UConn", "id": "11767", "name": "Caroline Ducharme", "year": "Freshman", "hometown": "Milton, Mass.", "high_school": null, "previous_school": "Noble & Greenough School", "height": "6'2\"", "position": "Guard", "jersey": "33", "url": "/sports/womens-basketball/roster/caroline-ducharme/11767", "season": "2000-01"}, {"team_id": 164, "team": "UConn", "id": "11765", "name": "Azzi Fudd", "year": "Freshman", "hometown": "Arlington, Va.", "high_school": null, "previous_school": "St. John's College HS", "height": "5'11\"", "position": "Guard", "jersey": "35", "url": "/sports/womens-basketball/roster/azzi-fudd/11765", "season": "2000-01"}, {"team_id": 164, "team": "UConn", "id": "11766", "name": "Amari DeBerry", "year": "Freshman", "hometown": "Williamsville, N.Y.", "high_school": null, "previous_school": "Williamsville South HS", "height": "6'5\"", "position": "Forward", "jersey": "42", "url": "/sports/womens-basketball/roster/amari-deberry/11766", "season": "2000-01"}, {"team_id": 164, "team": "UConn", "id": "11738", "name": "Aubrey Griffin", "year": "Junior", "hometown": "Ossining, N.Y.", "high_school": null, "previous_school": "Ossining HS", "height": "6'1\"", "position": "Forward", "jersey": "44", "url": "/sports/womens-basketball/roster/aubrey-griffin/11738", "season": "2000-01"}]