[{"team_id": 19651, "team": "High Point", "id": "5028", "name": "Tayler Tremblay", "year": "Senior", "hometown": "Boca Raton, Fla.", "high_school": "St. Andrew's", "previous_school": null, "height": "5'5\"", "position": "Guard", "jersey": "1", "url": "/sports/womens-basketball/roster/tayler-tremblay/5028", "season": "2013-14"}, {"team_id": 19651, "team": "High Point", "id": "5024", "name": "Lexi Patterson", "year": "Junior", "hometown": "Salem, Va.", "high_school": "Oak Hill Academy", "previous_school": null, "height": "5'6\"", "position": "Guard", "jersey": "2", "url": "/sports/womens-basketball/roster/lexi-patterson/5024", "season": "2013-14"}, {"team_id": 19651, "team": "High Point", "id": "5145", "name": "Kaylah Keys", "year": "Freshman", "hometown": "Memphis, Tenn.", "high_school": "Harding Academy", "previous_school": null, "height": "5'5\"", "position": "Guard", "jersey": "3", "url": "/sports/womens-basketball/roster/kaylah-keys/5145", "season": "2013-14"}, {"team_id": 19651, "team": "High Point", "id": "5027", "name": "Stacia Robertson", "year": "Redshirt Junior", "hometown": "Grand Island, Neb.", "high_school": "Grand Island (South Dakota)", "previous_school": null, "height": "6'2\"", "position": "Forward", "jersey": "4", "url": "/sports/womens-basketball/roster/stacia-robertson/5027", "season": "2013-14"}, {"team_id": 19651, "team": "High Point", "id": "5025", "name": "Lindsay Puckett", "year": "Redshirt Junior", "hometown": "Eden, N.C.", "high_school": "Rockingham County", "previous_school": null, "height": "5'11\"", "position": "Guard", "jersey": "10", "url": "/sports/womens-basketball/roster/lindsay-puckett/5025", "season": "2013-14"}, {"team_id": 19651, "team": "High Point", "id": "5141", "name": "DeAnneisha Jackson", "year": "Freshman", "hometown": "Angier, N.C.", "high_school": "Harnett Central", "previous_school": null, "height": "6'2\"", "position": "Forward", "jersey": "14", "url": "/sports/womens-basketball/roster/deanneisha-jackson/5141", "season": "2013-14"}, {"team_id": 19651, "team": "High Point", "id": "5140", "name": "Maja Michalska", "year": "Freshman", "hometown": "Piastow, Poland", "high_school": "Zespol Szkol Sportowych", "previous_school": null, "height": "5'7\"", "position": "Guard", "jersey": "15", "url": "/sports/womens-basketball/roster/maja-michalska/5140", "season": "2013-14"}, {"team_id": 19651, "team": "High Point", "id": "5026", "name": "Ashante Richard", "year": "Junior", "hometown": "Durham, N.C.", "high_school": "Northern", "previous_school": null, "height": "5'4\"", "position": "Guard", "jersey": "20", "url": "/sports/womens-basketball/roster/ashante-richard/5026", "season": "2013-14"}, {"team_id": 19651, "team": "High Point", "id": "5142", "name": "Latrice Phelps", "year": "Junior", "hometown": "Virginia Beach, Va.", "high_school": "Tallwood (Louisburg)", "previous_school": null, "height": "6'0\"", "position": "Forward", "jersey": "22", "url": "/sports/womens-basketball/roster/latrice-phelps/5142", "season": "2013-14"}, {"team_id": 19651, "team": "High Point", "id": "5146", "name": "Teddy Vincent", "year": "Freshman", "hometown": "Martin, Tenn.", "high_school": "Westview", "previous_school": null, "height": "5'10\"", "position": "Guard", "jersey": "23", "url": "/sports/womens-basketball/roster/teddy-vincent/5146", "season": "2013-14"}, {"team_id": 19651, "team": "High Point", "id": "5022", "name": "Tabitha Fudge", "year": "Sophomore", "hometown": "Snellville, Ga.", "high_school": "Miller Grove", "previous_school": null, "height": "6'2\"", "position": "Forward", "jersey": "32", "url": "/sports/womens-basketball/roster/tabitha-fudge/5022", "season": "2013-14"}, {"team_id": 19651, "team": "High Point", "id": "5023", "name": "Jatzmin Johnson", "year": "Sophomore", "hometown": "Concord, N.C.", "high_school": "Thomasville Prep", "previous_school": null, "height": "6'1\"", "position": "Forward", "jersey": "34", "url": "/sports/womens-basketball/roster/jatzmin-johnson/5023", "season": "2013-14"}]