[{"team_id": 428, "team": "Minnesota", "id": "8328", "name": "Brittney Davis", "year": "Freshman", "hometown": "Portland, Ore.", "high_school": "Jefferson", "previous_school": null, "height": "5'7\"", "position": "G", "jersey": "1", "url": "/sports/womens-basketball/roster/brittney-davis/8328", "season": "2004-05"}, {"team_id": 428, "team": "Minnesota", "id": "8326", "name": "Shannon Schonrock", "year": "Junior", "hometown": "Winnebago, Minn.", "high_school": "Blue Earth Area", "previous_school": null, "height": "5'6\"", "position": "G", "jersey": "11", "url": "/sports/womens-basketball/roster/shannon-schonrock/8326", "season": "2004-05"}, {"team_id": 428, "team": "Minnesota", "id": "8332", "name": "Natasha Williams", "year": "Freshman", "hometown": "Skokie, Ill.", "high_school": "Niles North", "previous_school": null, "height": "6'3\"", "position": "F", "jersey": "20", "url": "/sports/womens-basketball/roster/natasha-williams/8332", "season": "2004-05"}, {"team_id": 428, "team": "Minnesota", "id": "8319", "name": "Shannon Bolden", "year": "Junior", "hometown": "Marshall, Minn.", "high_school": "Marshall", "previous_school": null, "height": "5'11\"", "position": "G/F", "jersey": "22", "url": "/sports/womens-basketball/roster/shannon-bolden/8319", "season": "2004-05"}, {"team_id": 428, "team": "Minnesota", "id": "8331", "name": "Kelly Roysland", "year": "Sophomore", "hometown": "Fosston, Minn.", "high_school": "Fosston", "previous_school": null, "height": "5'9\"", "position": "G", "jersey": "3", "url": "/sports/womens-basketball/roster/kelly-roysland/8331", "season": "2004-05"}, {"team_id": 428, "team": "Minnesota", "id": "8323", "name": "Hannah Garry", "year": "Junior", "hometown": "Stewartville, Minn.", "high_school": "Stewartville", "previous_school": null, "height": "5'5\"", "position": "G", "jersey": "31", "url": "/sports/womens-basketball/roster/hannah-garry/8323", "season": "2004-05"}, {"team_id": 428, "team": "Minnesota", "id": "8327", "name": "Katie Alsdurf", "year": "Junior", "hometown": "Forest Lake, Minn.", "high_school": "Marquette", "previous_school": null, "height": null, "position": "G", "jersey": "32", "url": "/sports/womens-basketball/roster/katie-alsdurf/8327", "season": "2004-05"}, {"team_id": 428, "team": "Minnesota", "id": "8320", "name": "Jamie Broback", "year": "Sophomore", "hometown": "Apple Valley, Minn.", "high_school": "Eastview", "previous_school": null, "height": "6'3\"", "position": "G/F", "jersey": "33", "url": "/sports/womens-basketball/roster/jamie-broback/8320", "season": "2004-05"}, {"team_id": 428, "team": "Minnesota", "id": "8324", "name": "Lauren Lacey", "year": "Freshman", "hometown": "Olympia Fields, Ill.", "high_school": "Marian Catholic", "previous_school": null, "height": "6'3\"", "position": "F/C", "jersey": "34", "url": "/sports/womens-basketball/roster/lauren-lacey/8324", "season": "2004-05"}, {"team_id": 428, "team": "Minnesota", "id": "8330", "name": "Janel McCarville", "year": "Senior", "hometown": "Stevens Point, Wis.", "high_school": "Stevens Point", "previous_school": null, "height": "6'2\"", "position": "C", "jersey": "4", "url": "/sports/womens-basketball/roster/janel-mccarville/8330", "season": "2004-05"}, {"team_id": 428, "team": "Minnesota", "id": "8329", "name": "Leslie Knight", "year": "Freshman", "hometown": "Minnetonka, Minn.", "high_school": "Hopkins", "previous_school": null, "height": null, "position": "F", "jersey": "45", "url": "/sports/womens-basketball/roster/leslie-knight/8329", "season": "2004-05"}, {"team_id": 428, "team": "Minnesota", "id": "8321", "name": "April Calhoun", "year": "Junior", "hometown": "New Hope, Minn.", "high_school": null, "previous_school": null, "height": "5'8\"", "position": "G", "jersey": "5", "url": "/sports/womens-basketball/roster/april-calhoun/8321", "season": "2004-05"}, {"team_id": 428, "team": "Minnesota", "id": "8322", "name": "Christina Collison", "year": "Junior", "hometown": "Eden Prairie, Minn.", "high_school": "Eden Prairie", "previous_school": null, "height": "6'2\"", "position": "C", "jersey": "50", "url": "/sports/womens-basketball/roster/christina-collison/8322", "season": "2004-05"}, {"team_id": 428, "team": "Minnesota", "id": "8325", "name": "Liz Podominick", "year": "Sophomore", "hometown": "Lakeville, Minn.", "high_school": "Lakeville", "previous_school": null, "height": "6'2\"", "position": "F/C", "jersey": "55", "url": "/sports/womens-basketball/roster/liz-podominick/8325", "season": "2004-05"}]