[{"team_id": 43, "team": "Austin Peay", "id": "4163", "name": "Tiasha Gray", "year": "Senior", "hometown": "Clarksville, Tenn.", "high_school": "Clarksville HS", "previous_school": null, "height": "5'7\"", "position": "Guard", "jersey": "1", "url": "/sports/womens-basketball/roster/tiasha-gray/4163", "season": "2015-16"}, {"team_id": 43, "team": "Austin Peay", "id": "4284", "name": "J'Nayah Hall", "year": "Freshman", "hometown": "Owensboro, Ky.", "high_school": "Apollo HS", "previous_school": null, "height": "5'10\"", "position": "Guard", "jersey": "2", "url": "/sports/womens-basketball/roster/j-nayah-hall/4284", "season": "2015-16"}, {"team_id": 43, "team": "Austin Peay", "id": "4169", "name": "April Rivers", "year": "Junior", "hometown": "Las Vegas, Nev.", "high_school": "Bishop Gorman HS", "previous_school": null, "height": "5'5\"", "position": "Guard", "jersey": "3", "url": "/sports/womens-basketball/roster/april-rivers/4169", "season": "2015-16"}, {"team_id": 43, "team": "Austin Peay", "id": "4158", "name": "Brianne Alexander", "year": "Sophomore", "hometown": "Smyrna, Tenn.", "high_school": "Smyrna HS", "previous_school": null, "height": "6'0\"", "position": "Center", "jersey": "11", "url": "/sports/womens-basketball/roster/brianne-alexander/4158", "season": "2015-16"}, {"team_id": 43, "team": "Austin Peay", "id": "4168", "name": "Madison Rich", "year": "Sophomore", "hometown": "Bee Spring, Ky.", "high_school": "Edmonson HS", "previous_school": null, "height": "5'7\"", "position": "Guard", "jersey": "12", "url": "/sports/womens-basketball/roster/madison-rich/4168", "season": "2015-16"}, {"team_id": 43, "team": "Austin Peay", "id": "4401", "name": "Shelby Olszewski", "year": "Fifth Year", "hometown": "Pickerington, Ohio", "high_school": "Pickerington North HS", "previous_school": null, "height": "5'7\"", "position": "Guard", "jersey": "13", "url": "/sports/womens-basketball/roster/shelby-olszewski/4401", "season": "2015-16"}, {"team_id": 43, "team": "Austin Peay", "id": "4166", "name": "Jennifer Nwokocha", "year": "Senior", "hometown": "Atlanta, Ga.", "high_school": "Riverwood International Charter", "previous_school": null, "height": "5'11\"", "position": "Forward", "jersey": "21", "url": "/sports/womens-basketball/roster/jennifer-nwokocha/4166", "season": "2015-16"}, {"team_id": 43, "team": "Austin Peay", "id": "4285", "name": "Keisha Gregory", "year": "Freshman", "hometown": "Johnson City, Tenn.", "high_school": "Science Hill HS", "previous_school": null, "height": "5'10\"", "position": "Guard", "jersey": "22", "url": "/sports/womens-basketball/roster/keisha-gregory/4285", "season": "2015-16"}, {"team_id": 43, "team": "Austin Peay", "id": "4162", "name": "Sydney Gooch", "year": "Sophomore", "hometown": "Franklin, Ky.", "high_school": "Franklin-Simpson HS", "previous_school": null, "height": "5'10\"", "position": "Forward/Center", "jersey": "23", "url": "/sports/womens-basketball/roster/sydney-gooch/4162", "season": "2015-16"}, {"team_id": 43, "team": "Austin Peay", "id": "4167", "name": "Beth Rates", "year": "Junior", "hometown": "Hawesville, Ky.", "high_school": "Hancock County HS", "previous_school": null, "height": "5'11\"", "position": "Center", "jersey": "24", "url": "/sports/womens-basketball/roster/beth-rates/4167", "season": "2015-16"}, {"team_id": 43, "team": "Austin Peay", "id": "4160", "name": "Tearra Banks", "year": "Junior", "hometown": "Louisville, Ky.", "high_school": "Ballard HS", "previous_school": null, "height": "6'2\"", "position": "Center", "jersey": "25", "url": "/sports/womens-basketball/roster/tearra-banks/4160", "season": "2015-16"}, {"team_id": 43, "team": "Austin Peay", "id": "4159", "name": "Falon Baker", "year": "Sophomore", "hometown": "Portland, Tenn.", "high_school": "Beech HS", "previous_school": null, "height": "5'8\"", "position": "Guard", "jersey": "33", "url": "/sports/womens-basketball/roster/falon-baker/4159", "season": "2015-16"}, {"team_id": 43, "team": "Austin Peay", "id": "4165", "name": "Symantha Norton", "year": "Senior", "hometown": "Scottsburg, Ind.", "high_school": "Scottsburg HS", "previous_school": null, "height": "5'10\"", "position": "Guard/Forward", "jersey": "42", "url": "/sports/womens-basketball/roster/symantha-norton/4165", "season": "2015-16"}, {"team_id": 43, "team": "Austin Peay", "id": "4170", "name": "Jacey Scott", "year": "Junior", "hometown": "Douglas, Ala.", "high_school": "Douglas HS", "previous_school": null, "height": "5'9\"", "position": "Guard", "jersey": "44", "url": "/sports/womens-basketball/roster/jacey-scott/4170", "season": "2015-16"}, {"team_id": 43, "team": "Austin Peay", "id": "4164", "name": "Lauren Maki", "year": "Senior", "hometown": "Clarksville, Tenn.", "high_school": "Clarksville Academy", "previous_school": null, "height": "6'3\"", "position": "Center", "jersey": "54", "url": "/sports/womens-basketball/roster/lauren-maki/4164", "season": "2015-16"}]