[{"team_id": 457, "team": "North Carolina", "id": "8281", "name": "She'la White", "year": "Junior", "hometown": "Portsmouth, Va.", "high_school": "Norfolk Collegiate", "previous_school": null, "height": "5'5\"", "position": "Guard", "jersey": "1", "url": "/sports/womens-basketball/roster/she-la-white/8281", "season": "2010-11"}, {"team_id": 457, "team": "North Carolina", "id": "8272", "name": "Latifah Coleman", "year": "Freshman", "hometown": "Pageland, S.C.", "high_school": "Central", "previous_school": null, "height": "5'9\"", "position": "Guard", "jersey": "2", "url": "/sports/womens-basketball/roster/latifah-coleman/8272", "season": "2010-11"}, {"team_id": 457, "team": "North Carolina", "id": "8282", "name": "Candace Wood", "year": "Sophomore", "hometown": "Charlotte, N.C.", "high_school": "Victory Christian Center", "previous_school": null, "height": "5'11\"", "position": "Guard", "jersey": "4", "url": "/sports/womens-basketball/roster/candace-wood/8282", "season": "2010-11"}, {"team_id": 457, "team": "North Carolina", "id": "8276", "name": "Nicole Powell", "year": "Senior", "hometown": "Asheville, N.C.", "high_school": "Asheville", "previous_school": null, "height": "5'10\"", "position": "Guard", "jersey": "5", "url": "/sports/womens-basketball/roster/nicole-powell/8276", "season": "2010-11"}, {"team_id": 457, "team": "North Carolina", "id": "8280", "name": "Shannon Smith", "year": "Freshman", "hometown": "Battle Creek, Mich.", "high_school": "Lakeview", "previous_school": null, "height": "5'7\"", "position": "Guard", "jersey": "15", "url": "/sports/womens-basketball/roster/shannon-smith/8280", "season": "2010-11"}, {"team_id": 457, "team": "North Carolina", "id": "8279", "name": "Chay Shegog", "year": "Junior", "hometown": "Stafford, Va.", "high_school": "Brook Point", "previous_school": null, "height": "6'5\"", "position": "Foward/Center", "jersey": "20", "url": "/sports/womens-basketball/roster/chay-shegog/8279", "season": "2010-11"}, {"team_id": 457, "team": "North Carolina", "id": "8274", "name": "Krista Gross", "year": "Sophomore", "hometown": "Charlotte, N.C.", "high_school": "Cannon School", "previous_school": null, "height": "6'0\"", "position": "Guard", "jersey": "21", "url": "/sports/womens-basketball/roster/krista-gross/8274", "season": "2010-11"}, {"team_id": 457, "team": "North Carolina", "id": "8273", "name": "Cetera DeGraffenreid", "year": "Senior", "hometown": "Cullowhee, N.C.", "high_school": "Smoky Mountain", "previous_school": null, "height": "5'6\"", "position": "Guard", "jersey": "22", "url": "/sports/womens-basketball/roster/cetera-degraffenreid/8273", "season": "2010-11"}, {"team_id": 457, "team": "North Carolina", "id": "8277", "name": "Waltiea Rolle", "year": "Sophomore", "hometown": "Nassau, Bahamas", "high_school": "Westbury Christian School", "previous_school": null, "height": "6'6\"", "position": "Foward/Center", "jersey": "32", "url": "/sports/womens-basketball/roster/waltiea-rolle/8277", "season": "2010-11"}, {"team_id": 457, "team": "North Carolina", "id": "8271", "name": "Laura Broomfield", "year": "Junior", "hometown": "Lexington Park, Md.", "high_school": "St. Mary's Ryken", "previous_school": null, "height": "6'1\"", "position": "Forward", "jersey": "33", "url": "/sports/womens-basketball/roster/laura-broomfield/8271", "season": "2010-11"}, {"team_id": 457, "team": "North Carolina", "id": "8278", "name": "Tierra Ruffin-Pratt", "year": "Sophomore", "hometown": "Alexandria, Va.", "high_school": "T.C. Williams", "previous_school": null, "height": "5'10\"", "position": "Guard", "jersey": "44", "url": "/sports/womens-basketball/roster/tierra-ruffin-pratt/8278", "season": "2010-11"}, {"team_id": 457, "team": "North Carolina", "id": "8275", "name": "Italee Lucas", "year": "Senior", "hometown": "Las Vegas, Nev.", "high_school": "Centennial", "previous_school": null, "height": "5'8\"", "position": "Guard", "jersey": "50", "url": "/sports/womens-basketball/roster/italee-lucas/8275", "season": "2010-11"}, {"team_id": 457, "team": "North Carolina", "id": "8270", "name": "Jessica Breland", "year": "Senior", "hometown": "Kelford, N.C.", "high_school": null, "previous_school": null, "height": "6'3\"", "position": "Forward", "jersey": "51", "url": "/sports/womens-basketball/roster/jessica-breland/8270", "season": "2010-11"}]