[{"team_id": 663, "team": "Southern Methodist", "id": "743", "name": "Kristin Hernandez", "year": "RS JR", "hometown": "Duncanville, Texas", "high_school": null, "previous_school": null, "height": "5'9\"", "position": "Guard", "jersey": "2", "url": "/sports/womens-basketball/roster/kristin-hernandez/743", "season": "2010-11"}, {"team_id": 663, "team": "Southern Methodist", "id": "749", "name": "Delisha Wills", "year": "RS SR", "hometown": "Mesquite, Texas", "high_school": "Mesquite", "previous_school": null, "height": "5'10\"", "position": "Forward", "jersey": "5", "url": "/sports/womens-basketball/roster/delisha-wills/749", "season": "2010-11"}, {"team_id": 663, "team": "Southern Methodist", "id": "738", "name": "Heidi Brandenburg", "year": "RS JR", "hometown": "Garland, Texas", "high_school": "Missouri", "previous_school": null, "height": "6'3\"", "position": "Post / Forward", "jersey": "20", "url": "/sports/womens-basketball/roster/heidi-brandenburg/738", "season": "2010-11"}, {"team_id": 663, "team": "Southern Methodist", "id": "741", "name": "Christine Elliott", "year": "JR", "hometown": "Wichita, Kan.", "high_school": "South", "previous_school": null, "height": "6'2\"", "position": "Post", "jersey": "21", "url": "/sports/womens-basketball/roster/christine-elliott/741", "season": "2010-11"}, {"team_id": 663, "team": "Southern Methodist", "id": "742", "name": "Alisha Filmore", "year": "SO", "hometown": "Mansfield, Texas", "high_school": "Summit", "previous_school": null, "height": "5'7\"", "position": "Guard", "jersey": "22", "url": "/sports/womens-basketball/roster/alisha-filmore/742", "season": "2010-11"}, {"team_id": 663, "team": "Southern Methodist", "id": "747", "name": "Akil Simpson", "year": "FR", "hometown": "Duncanville, Texas", "high_school": "Duncanville", "previous_school": null, "height": "6'0\"", "position": "Forward", "jersey": "23", "url": "/sports/womens-basketball/roster/akil-simpson/747", "season": "2010-11"}, {"team_id": 663, "team": "Southern Methodist", "id": "740", "name": "Haley Day", "year": "SR", "hometown": "Rockwall, Texas", "high_school": "Rockwall", "previous_school": null, "height": "5'10\"", "position": "Guard/Forward", "jersey": "24", "url": "/sports/womens-basketball/roster/haley-day/740", "season": "2010-11"}, {"team_id": 663, "team": "Southern Methodist", "id": "744", "name": "Krystal Johnson", "year": "FR", "hometown": "Garland, Texas", "high_school": "Naaman Forest", "previous_school": null, "height": "5'5\"", "position": "Guard", "jersey": "25", "url": "/sports/womens-basketball/roster/krystal-johnson/744", "season": "2010-11"}, {"team_id": 663, "team": "Southern Methodist", "id": "746", "name": "Raven Short", "year": "FR", "hometown": "Flower Mound, Texas", "high_school": "Marcus", "previous_school": null, "height": "5'11\"", "position": "Guard", "jersey": "32", "url": "/sports/womens-basketball/roster/raven-short/746", "season": "2010-11"}, {"team_id": 663, "team": "Southern Methodist", "id": "745", "name": "Samantha Mahnesmith", "year": "JR", "hometown": "Kennedale, Texas", "high_school": "Kennedale High School", "previous_school": null, "height": "5'8\"", "position": "Guard", "jersey": "33", "url": "/sports/womens-basketball/roster/samantha-mahnesmith/745", "season": "2010-11"}, {"team_id": 663, "team": "Southern Methodist", "id": "739", "name": "Raquel Christian", "year": "RS SR", "hometown": "Midland, Texas", "high_school": "Texas Tech", "previous_school": null, "height": "5'6\"", "position": "Guard", "jersey": "35", "url": "/sports/womens-basketball/roster/raquel-christian/739", "season": "2010-11"}, {"team_id": 663, "team": "Southern Methodist", "id": "748", "name": "Mallory Singleton", "year": "FR", "hometown": "Flower Mound, Texas", "high_school": "Flower Mound", "previous_school": null, "height": "6'2\"", "position": "Post", "jersey": "44", "url": "/sports/womens-basketball/roster/mallory-singleton/748", "season": "2010-11"}]