[{"team_id": 690, "team": "Temple", "id": "8815", "name": "Alliya Butts", "year": "Junior", "hometown": "Edgewater Park, N.J.", "high_school": "Holy Cross", "previous_school": null, "height": "5'4\"", "position": "G", "jersey": "0", "url": "/sports/womens-basketball/roster/alliya-butts/8815", "season": "2016-17"}, {"team_id": 690, "team": "Temple", "id": "8820", "name": "Lena Niang", "year": "Sophomore", "hometown": "Dakar, Senegal", "high_school": "Riverdale Baptist (Md.)", "previous_school": "NC State", "height": "6'2\"", "position": "F", "jersey": "1", "url": "/sports/womens-basketball/roster/lena-niang/8820", "season": "2016-17"}, {"team_id": 690, "team": "Temple", "id": "8816", "name": "Feyonda Fitzgerald", "year": "Senior", "hometown": "Norfolk, Va.", "high_school": "Lake Taylor", "previous_school": null, "height": "5'7\"", "position": "G", "jersey": "2", "url": "/sports/womens-basketball/roster/feyonda-fitzgerald/8816", "season": "2016-17"}, {"team_id": 690, "team": "Temple", "id": "8823", "name": "Takora McIntyre", "year": "Freshman", "hometown": "Boston, Mass.", "high_school": "Fenway High", "previous_school": null, "height": "5'5\"", "position": "G", "jersey": "4", "url": "/sports/womens-basketball/roster/takora-mcintyre/8823", "season": "2016-17"}, {"team_id": 690, "team": "Temple", "id": "8821", "name": "Shannen Atkinson", "year": "Freshman", "hometown": "Smithfield, Va.", "high_school": "Smithfield", "previous_school": null, "height": "6'4\"", "position": "C", "jersey": "11", "url": "/sports/womens-basketball/roster/shannen-atkinson/8821", "season": "2016-17"}, {"team_id": 690, "team": "Temple", "id": "8819", "name": "Ruth Sherrill", "year": "Senior", "hometown": "Alexandria, Va.", "high_school": "Thomas Edison", "previous_school": "Hofstra", "height": "6'0\"", "position": "F", "jersey": "12", "url": "/sports/womens-basketball/roster/ruth-sherrill/8819", "season": "2016-17"}, {"team_id": 690, "team": "Temple", "id": "8813", "name": "Khadijah Berger", "year": "Junior", "hometown": "Hampton, Va.", "high_school": "Hampton", "previous_school": null, "height": "5'10\"", "position": "G", "jersey": "21", "url": "/sports/womens-basketball/roster/khadijah-berger/8813", "season": "2016-17"}, {"team_id": 690, "team": "Temple", "id": "8812", "name": "Tanaya Atkinson", "year": "Junior", "hometown": "New Haven, Conn.", "high_school": "Hill Regional Career", "previous_school": null, "height": "5'9\"", "position": "G", "jersey": "22", "url": "/sports/womens-basketball/roster/tanaya-atkinson/8812", "season": "2016-17"}, {"team_id": 690, "team": "Temple", "id": "8825", "name": "Deja Reynolds", "year": "Sophomore", "hometown": "Philadelphia, Pa.", "high_school": "Imhotep Charter", "previous_school": null, "height": "5'9\"", "position": "G", "jersey": "23", "url": "/sports/womens-basketball/roster/deja-reynolds/8825", "season": "2016-17"}, {"team_id": 690, "team": "Temple", "id": "8822", "name": "Shantay Taylor", "year": "Freshman", "hometown": "Columbia, S.C.", "high_school": "Spring Valley", "previous_school": null, "height": "6'3\"", "position": "F", "jersey": "24", "url": "/sports/womens-basketball/roster/shantay-taylor/8822", "season": "2016-17"}, {"team_id": 690, "team": "Temple", "id": "8817", "name": "Donnaizha Fountain", "year": "Junior", "hometown": "Roxbury, Mass.", "high_school": "Cambridge Rindge & Latin", "previous_school": "Georgia Tech", "height": "6'0\"", "position": "G", "jersey": "32", "url": "/sports/womens-basketball/roster/donnaizha-fountain/8817", "season": "2016-17"}, {"team_id": 690, "team": "Temple", "id": "8814", "name": "Monasia Bolduc", "year": "Senior", "hometown": "Clintondale, N.Y.", "high_school": "Nazereth Academy", "previous_school": "Walters State", "height": "6'2\"", "position": "F", "jersey": "34", "url": "/sports/womens-basketball/roster/monasia-bolduc/8814", "season": "2016-17"}, {"team_id": 690, "team": "Temple", "id": "8818", "name": "Safiya Martin", "year": "Senior", "hometown": "Fayetteville, Ga.", "high_school": "Sandy Creek", "previous_school": null, "height": "6'4\"", "position": "C", "jersey": "35", "url": "/sports/womens-basketball/roster/safiya-martin/8818", "season": "2016-17"}]