[{"team_id": 71, "team": "Bowling Green", "id": "5524", "name": "Rachel Myers", "year": "Sophomore", "hometown": "Findlay, Ohio", "high_school": "Liberty-Benton", "previous_school": null, "height": "5'8\"", "position": "Guard", "jersey": "11", "url": "/sports/womens-basketball/roster/rachel-myers/5524", "season": "2015-16"}, {"team_id": 71, "team": "Bowling Green", "id": "5523", "name": "Rachel Konieczki", "year": "Junior", "hometown": "Rockford, Ill.", "high_school": "Rockford Lutheran", "previous_school": null, "height": "5'3\"", "position": "Guard", "jersey": "12", "url": "/sports/womens-basketball/roster/rachel-konieczki/5523", "season": "2015-16"}, {"team_id": 71, "team": "Bowling Green", "id": "5572", "name": "Sydney Lambert", "year": "Freshman", "hometown": "Cincinnati, Ohio", "high_school": "McAuley", "previous_school": null, "height": "5'8\"", "position": "Guard", "jersey": "13", "url": "/sports/womens-basketball/roster/sydney-lambert/5572", "season": "2015-16"}, {"team_id": 71, "team": "Bowling Green", "id": "5573", "name": "Carly Santoro", "year": "Freshman", "hometown": "Bellevue, Ohio", "high_school": "Bellevue", "previous_school": null, "height": "5'10\"", "position": "Guard", "jersey": "14", "url": "/sports/womens-basketball/roster/carly-santoro/5573", "season": "2015-16"}, {"team_id": 71, "team": "Bowling Green", "id": "5518", "name": "Sarah Baer", "year": "Sophomore", "hometown": "Perrysburg, Ohio", "high_school": "Perrysburg", "previous_school": null, "height": "6'1\"", "position": "Center", "jersey": "20", "url": "/sports/womens-basketball/roster/sarah-baer/5518", "season": "2015-16"}, {"team_id": 71, "team": "Bowling Green", "id": "5522", "name": "Kennedy Kirkpatrick", "year": "Redshirt Sophomore", "hometown": "Lawrence, Kansas", "high_school": "Free State", "previous_school": null, "height": "5'10\"", "position": "Guard", "jersey": "23", "url": "/sports/womens-basketball/roster/kennedy-kirkpatrick/5522", "season": "2015-16"}, {"team_id": 71, "team": "Bowling Green", "id": "5519", "name": "Leah Bolton", "year": "Junior", "hometown": "Chicago, Ill.", "high_school": "Marist", "previous_school": null, "height": "5'11\"", "position": "Forward", "jersey": "24", "url": "/sports/womens-basketball/roster/leah-bolton/5519", "season": "2015-16"}, {"team_id": 71, "team": "Bowling Green", "id": "5521", "name": "Miriam Justinger", "year": "Senior", "hometown": "Sylvania, Ohio", "high_school": "Northview", "previous_school": null, "height": "6'0\"", "position": "Guard/Forward", "jersey": "30", "url": "/sports/womens-basketball/roster/miriam-justinger/5521", "season": "2015-16"}, {"team_id": 71, "team": "Bowling Green", "id": "5527", "name": "Lauren Tibbs", "year": "Redshirt Senior", "hometown": "Taylor Mill, Ky.", "high_school": "Scott", "previous_school": "Marquette Univ.", "height": "6'4\"", "position": "Center", "jersey": "32", "url": "/sports/womens-basketball/roster/lauren-tibbs/5527", "season": "2015-16"}, {"team_id": 71, "team": "Bowling Green", "id": "5525", "name": "Haley Puk", "year": "Sophomore", "hometown": "Waterloo, Iowa", "high_school": "Waterloo West", "previous_school": null, "height": "6'0\"", "position": "Guard", "jersey": "33", "url": "/sports/womens-basketball/roster/haley-puk/5525", "season": "2015-16"}, {"team_id": 71, "team": "Bowling Green", "id": "5528", "name": "Ashley Tunstall", "year": "Junior", "hometown": "Dayton, Ohio", "high_school": "Huber Heights Wayne", "previous_school": "Owens CC", "height": "5'10\"", "position": "Forward", "jersey": "34", "url": "/sports/womens-basketball/roster/ashley-tunstall/5528", "season": "2015-16"}, {"team_id": 71, "team": "Bowling Green", "id": "5526", "name": "Abby Siefker", "year": "Junior", "hometown": "Ottoville, Ohio", "high_school": "Ottoville", "previous_school": null, "height": "6'2\"", "position": "Center", "jersey": "43", "url": "/sports/womens-basketball/roster/abby-siefker/5526", "season": "2015-16"}, {"team_id": 71, "team": "Bowling Green", "id": "5571", "name": "Maddie Cole", "year": "Freshman", "hometown": "Sylvania, Ohio", "high_school": "Northview", "previous_school": null, "height": "6'0\"", "position": "Forward", "jersey": "44", "url": "/sports/womens-basketball/roster/maddie-cole/5571", "season": "2015-16"}]